<?xml version="1.0" encoding="UTF-8"?>
<!DOCTYPE AttributeServer>
<Profile Version="1.3">
    <SetupId>0</SetupId>
    <Device>nRF8001_Dx</Device>
    <Service Type="local" PrimaryService="true">
        <Name>Controller </Name>
        <Uuid BaseUUID="8C6B0000A312681D025B0032C0D16A2D" BaseUUIDName="BLEduino">f001</Uuid>
        <Characteristic>
            <Name>Button Action</Name>
            <Uuid BaseUUID="8C6B0000A312681D025B0032C0D16A2D" BaseUUIDName="BLEduino">d00d</Uuid>
            <DefaultValue></DefaultValue>
            <UsePresentationFormat>0</UsePresentationFormat>
            <UserDescription></UserDescription>
            <MaxDataLength>5</MaxDataLength>
            <AttributeLenType>1</AttributeLenType>
            <ForceOpen>false</ForceOpen>
            <Properties>
                <WriteWithoutResponse>true</WriteWithoutResponse>
                <Write>true</Write>
                <Notify>false</Notify>
                <Indicate>false</Indicate>
                <Broadcast>false</Broadcast>
            </Properties>
            <SetPipe>false</SetPipe>
            <AckIsAuto>true</AckIsAuto>
            <PresentationFormatDescriptor Value="0000" Exponent="0" Format="1" NameSpace="01" Unit="0000"/>
            <PeriodForReadingThisCharacteristic>0</PeriodForReadingThisCharacteristic>
            <PeriodForProperties/>
        </Characteristic>
    </Service>
    <Service Type="local" PrimaryService="true">
        <Name>Firmata</Name>
        <Uuid BaseUUID="8C6B0000A312681D025B0032C0D16A2D" BaseUUIDName="BLEduino">1ed1</Uuid>
        <Characteristic>
            <Name>Firmata Command</Name>
            <Uuid BaseUUID="8C6B0000A312681D025B0032C0D16A2D" BaseUUIDName="BLEduino">2551</Uuid>
            <DefaultValue></DefaultValue>
            <UsePresentationFormat>0</UsePresentationFormat>
            <UserDescription></UserDescription>
            <MaxDataLength>4</MaxDataLength>
            <AttributeLenType>1</AttributeLenType>
            <ForceOpen>false</ForceOpen>
            <Properties>
                <WriteWithoutResponse>true</WriteWithoutResponse>
                <Write>true</Write>
                <Notify>true</Notify>
                <Indicate>true</Indicate>
                <Broadcast>false</Broadcast>
            </Properties>
            <SetPipe>true</SetPipe>
            <AckIsAuto>true</AckIsAuto>
            <PresentationFormatDescriptor Value="0000" Exponent="0" Format="1" NameSpace="01" Unit="0000"/>
            <PeriodForReadingThisCharacteristic>0</PeriodForReadingThisCharacteristic>
            <PeriodForProperties/>
        </Characteristic>
    </Service>
    <Service Type="local" PrimaryService="true">
        <Name>UART</Name>
        <Uuid BaseUUID="8C6B0000A312681D025B0032C0D16A2D" BaseUUIDName="BLEduino">da7a</Uuid>
        <Characteristic>
            <Name>RX</Name>
            <Uuid BaseUUID="8C6B0000A312681D025B0032C0D16A2D" BaseUUIDName="BLEduino">abcd</Uuid>
            <DefaultValue></DefaultValue>
            <UsePresentationFormat>0</UsePresentationFormat>
            <UserDescription></UserDescription>
            <MaxDataLength>20</MaxDataLength>
            <AttributeLenType>2</AttributeLenType>
            <ForceOpen>false</ForceOpen>
            <Properties>
                <WriteWithoutResponse>true</WriteWithoutResponse>
                <Write>true</Write>
                <Notify>false</Notify>
                <Indicate>false</Indicate>
                <Broadcast>false</Broadcast>
            </Properties>
            <SetPipe>false</SetPipe>
            <AckIsAuto>true</AckIsAuto>
            <PresentationFormatDescriptor Value="0000" Exponent="0" Format="1" NameSpace="01" Unit="0000"/>
            <PeriodForReadingThisCharacteristic>0</PeriodForReadingThisCharacteristic>
            <PeriodForProperties/>
        </Characteristic>
        <Characteristic>
            <Name>TX</Name>
            <Uuid BaseUUID="8C6B0000A312681D025B0032C0D16A2D" BaseUUIDName="BLEduino">1010</Uuid>
            <DefaultValue></DefaultValue>
            <UsePresentationFormat>0</UsePresentationFormat>
            <UserDescription></UserDescription>
            <MaxDataLength>20</MaxDataLength>
            <AttributeLenType>2</AttributeLenType>
            <ForceOpen>false</ForceOpen>
            <Properties>
                <WriteWithoutResponse>false</WriteWithoutResponse>
                <Write>false</Write>
                <Notify>false</Notify>
                <Indicate>false</Indicate>
                <Broadcast>false</Broadcast>
            </Properties>
            <SetPipe>false</SetPipe>
            <AckIsAuto>false</AckIsAuto>
            <PresentationFormatDescriptor Value="0000" Exponent="0" Format="1" NameSpace="01" Unit="0000"/>
            <PeriodForReadingThisCharacteristic>0</PeriodForReadingThisCharacteristic>
            <PeriodForProperties/>
        </Characteristic>
    </Service>
    <Service Type="local" PrimaryService="true">
        <Name>Notification</Name>
        <Uuid BaseUUID="8C6B0000A312681D025B0032C0D16A2D" BaseUUIDName="BLEduino">3141</Uuid>
        <Characteristic>
            <Name>Notification Attributes</Name>
            <Uuid BaseUUID="8C6B0000A312681D025B0032C0D16A2D" BaseUUIDName="BLEduino">1618</Uuid>
            <DefaultValue></DefaultValue>
            <UsePresentationFormat>0</UsePresentationFormat>
            <UserDescription>The notification attributes, including message and title.</UserDescription>
            <MaxDataLength>20</MaxDataLength>
            <AttributeLenType>2</AttributeLenType>
            <ForceOpen>false</ForceOpen>
            <Properties>
                <WriteWithoutResponse>true</WriteWithoutResponse>
                <Write>true</Write>
                <Notify>false</Notify>
                <Indicate>false</Indicate>
                <Broadcast>false</Broadcast>
            </Properties>
            <SetPipe>false</SetPipe>
            <AckIsAuto>true</AckIsAuto>
            <PresentationFormatDescriptor Value="0000" Exponent="0" Format="1" NameSpace="01" Unit="0000"/>
            <PeriodForReadingThisCharacteristic>0</PeriodForReadingThisCharacteristic>
            <PeriodForProperties/>
        </Characteristic>
    </Service>
    <Service Type="local" PrimaryService="true">
        <Name>BLE Bridge</Name>
        <Uuid BaseUUID="8C6B0000A312681D025B0032C0D16A2D" BaseUUIDName="BLEduino">b1eb</Uuid>
        <Characteristic>
            <Name>Device ID</Name>
            <Uuid BaseUUID="8C6B0000A312681D025B0032C0D16A2D" BaseUUIDName="BLEduino">d1d0</Uuid>
            <DefaultValue></DefaultValue>
            <UsePresentationFormat>0</UsePresentationFormat>
            <UserDescription>The device ID given to the BLE slave.</UserDescription>
            <MaxDataLength>1</MaxDataLength>
            <AttributeLenType>1</AttributeLenType>
            <ForceOpen>false</ForceOpen>
            <Properties>
                <WriteWithoutResponse>true</WriteWithoutResponse>
                <Write>true</Write>
                <Notify>true</Notify>
                <Indicate>true</Indicate>
                <Broadcast>false</Broadcast>
            </Properties>
            <SetPipe>true</SetPipe>
            <AckIsAuto>true</AckIsAuto>
            <PresentationFormatDescriptor Value="0000" Exponent="0" Format="25" NameSpace="01" Unit="0000"/>
            <PeriodForReadingThisCharacteristic>0</PeriodForReadingThisCharacteristic>
            <PeriodForProperties/>
        </Characteristic>
        <Characteristic>
            <Name>Bridge Rx</Name>
            <Uuid BaseUUID="8C6B0000A312681D025B0032C0D16A2D" BaseUUIDName="BLEduino">5778</Uuid>
            <DefaultValue></DefaultValue>
            <UsePresentationFormat>0</UsePresentationFormat>
            <UserDescription>The message to be sent from another BLE slave device.</UserDescription>
            <MaxDataLength>20</MaxDataLength>
            <AttributeLenType>2</AttributeLenType>
            <ForceOpen>false</ForceOpen>
            <Properties>
                <WriteWithoutResponse>true</WriteWithoutResponse>
                <Write>true</Write>
                <Notify>false</Notify>
                <Indicate>false</Indicate>
                <Broadcast>false</Broadcast>
            </Properties>
            <SetPipe>false</SetPipe>
            <AckIsAuto>true</AckIsAuto>
            <PresentationFormatDescriptor Value="0000" Exponent="0" Format="1" NameSpace="01" Unit="0000"/>
            <PeriodForReadingThisCharacteristic>0</PeriodForReadingThisCharacteristic>
            <PeriodForProperties/>
        </Characteristic>
        <Characteristic>
            <Name>Bridge Tx</Name>
            <Uuid BaseUUID="8C6B0000A312681D025B0032C0D16A2D" BaseUUIDName="BLEduino">454b</Uuid>
            <DefaultValue></DefaultValue>
            <UsePresentationFormat>0</UsePresentationFormat>
            <UserDescription>The data to be sent to another BLE slave.</UserDescription>
            <MaxDataLength>20</MaxDataLength>
            <AttributeLenType>2</AttributeLenType>
            <ForceOpen>false</ForceOpen>
            <Properties>
                <WriteWithoutResponse>false</WriteWithoutResponse>
                <Write>false</Write>
                <Notify>true</Notify>
                <Indicate>true</Indicate>
                <Broadcast>false</Broadcast>
            </Properties>
            <SetPipe>false</SetPipe>
            <AckIsAuto>false</AckIsAuto>
            <PresentationFormatDescriptor Value="0000" Exponent="0" Format="1" NameSpace="01" Unit="0000"/>
            <PeriodForReadingThisCharacteristic>0</PeriodForReadingThisCharacteristic>
            <PeriodForProperties/>
        </Characteristic>
    </Service>
    <Service Type="local" PrimaryService="true">
        <Name>Vehicle Motion</Name>
        <Uuid BaseUUID="8C6B0000A312681D025B0032C0D16A2D" BaseUUIDName="BLEduino">1125</Uuid>
        <Characteristic>
            <Name>Throttle Yaw Roll Pitch</Name>
            <Uuid BaseUUID="8C6B0000A312681D025B0032C0D16A2D" BaseUUIDName="BLEduino">9806</Uuid>
            <DefaultValue></DefaultValue>
            <UsePresentationFormat>0</UsePresentationFormat>
            <UserDescription>The speed and orientation in which the vehicle is moving.</UserDescription>
            <MaxDataLength>4</MaxDataLength>
            <AttributeLenType>1</AttributeLenType>
            <ForceOpen>false</ForceOpen>
            <Properties>
                <WriteWithoutResponse>true</WriteWithoutResponse>
                <Write>true</Write>
                <Notify>false</Notify>
                <Indicate>false</Indicate>
                <Broadcast>false</Broadcast>
            </Properties>
            <SetPipe>false</SetPipe>
            <AckIsAuto>true</AckIsAuto>
            <PresentationFormatDescriptor Value="0000" Exponent="0" Format="1" NameSpace="01" Unit="0000"/>
            <PeriodForReadingThisCharacteristic>0</PeriodForReadingThisCharacteristic>
            <PeriodForProperties/>
        </Characteristic>
    </Service>
    <Service Type="local" PrimaryService="true">
        <Name>BLEduino</Name>
        <Uuid BaseUUID="8C6B0000A312681D025B0032C0D16A2D" BaseUUIDName="BLEduino">2013</Uuid>
        <Characteristic>
            <Name>Manufacturer Name String</Name>
            <Uuid>2a29</Uuid>
            <DefaultValue>Kytelabs</DefaultValue>
            <UsePresentationFormat>1</UsePresentationFormat>
            <UserDescription></UserDescription>
            <MaxDataLength>10</MaxDataLength>
            <AttributeLenType>1</AttributeLenType>
            <ForceOpen>false</ForceOpen>
            <Properties>
                <WriteWithoutResponse>false</WriteWithoutResponse>
                <Write>false</Write>
                <Notify>false</Notify>
                <Indicate>false</Indicate>
                <Broadcast>false</Broadcast>
            </Properties>
            <SetPipe>true</SetPipe>
            <AckIsAuto>false</AckIsAuto>
            <PresentationFormatDescriptor Value="0000" Exponent="0" Format="25" NameSpace="01" Unit="0000"/>
            <PeriodForReadingThisCharacteristic>0</PeriodForReadingThisCharacteristic>
            <PeriodForProperties/>
        </Characteristic>
    </Service>
    <Service Type="local" PrimaryService="true">
        <Name>Device Information</Name>
        <Uuid>180a</Uuid>
        <Characteristic>
            <Name>Model Number String</Name>
            <Uuid>2a24</Uuid>
            <DefaultValue>BLEduino</DefaultValue>
            <UsePresentationFormat>1</UsePresentationFormat>
            <UserDescription></UserDescription>
            <MaxDataLength>15</MaxDataLength>
            <AttributeLenType>1</AttributeLenType>
            <ForceOpen>false</ForceOpen>
            <Properties>
                <WriteWithoutResponse>false</WriteWithoutResponse>
                <Write>false</Write>
                <Notify>false</Notify>
                <Indicate>false</Indicate>
                <Broadcast>false</Broadcast>
            </Properties>
            <SetPipe>false</SetPipe>
            <AckIsAuto>false</AckIsAuto>
            <PresentationFormatDescriptor Value="0000" Exponent="0" Format="25" NameSpace="01" Unit="0000"/>
            <PeriodForReadingThisCharacteristic>0</PeriodForReadingThisCharacteristic>
            <PeriodForProperties/>
        </Characteristic>
        <Characteristic>
            <Name>Firmware Revision String</Name>
            <Uuid>2a26</Uuid>
            <DefaultValue>1.0</DefaultValue>
            <UsePresentationFormat>1</UsePresentationFormat>
            <UserDescription></UserDescription>
            <MaxDataLength>4</MaxDataLength>
            <AttributeLenType>1</AttributeLenType>
            <ForceOpen>false</ForceOpen>
            <Properties>
                <WriteWithoutResponse>false</WriteWithoutResponse>
                <Write>false</Write>
                <Notify>false</Notify>
                <Indicate>false</Indicate>
                <Broadcast>false</Broadcast>
            </Properties>
            <SetPipe>false</SetPipe>
            <AckIsAuto>false</AckIsAuto>
            <PresentationFormatDescriptor Value="0000" Exponent="0" Format="25" NameSpace="01" Unit="0000"/>
            <PeriodForReadingThisCharacteristic>0</PeriodForReadingThisCharacteristic>
            <PeriodForProperties/>
        </Characteristic>
        <Characteristic>
            <Name>Manufacturer Name String</Name>
            <Uuid>2a29</Uuid>
            <DefaultValue>Kytelabs</DefaultValue>
            <UsePresentationFormat>1</UsePresentationFormat>
            <UserDescription></UserDescription>
            <MaxDataLength>10</MaxDataLength>
            <AttributeLenType>1</AttributeLenType>
            <ForceOpen>false</ForceOpen>
            <Properties>
                <WriteWithoutResponse>false</WriteWithoutResponse>
                <Write>false</Write>
                <Notify>false</Notify>
                <Indicate>false</Indicate>
                <Broadcast>false</Broadcast>
            </Properties>
            <SetPipe>false</SetPipe>
            <AckIsAuto>false</AckIsAuto>
            <PresentationFormatDescriptor Value="0000" Exponent="0" Format="25" NameSpace="01" Unit="0000"/>
            <PeriodForReadingThisCharacteristic>0</PeriodForReadingThisCharacteristic>
            <PeriodForProperties/>
        </Characteristic>
        <Characteristic>
            <Name>Software Revision String</Name>
            <Uuid>2a28</Uuid>
            <DefaultValue>Rev1.0</DefaultValue>
            <UsePresentationFormat>1</UsePresentationFormat>
            <UserDescription></UserDescription>
            <MaxDataLength>10</MaxDataLength>
            <AttributeLenType>2</AttributeLenType>
            <ForceOpen>false</ForceOpen>
            <Properties>
                <WriteWithoutResponse>false</WriteWithoutResponse>
                <Write>false</Write>
                <Notify>false</Notify>
                <Indicate>false</Indicate>
                <Broadcast>false</Broadcast>
            </Properties>
            <SetPipe>false</SetPipe>
            <AckIsAuto>false</AckIsAuto>
            <PresentationFormatDescriptor Value="0000" Exponent="0" Format="25" NameSpace="01" Unit="0000"/>
            <PeriodForReadingThisCharacteristic>0</PeriodForReadingThisCharacteristic>
            <PeriodForProperties/>
        </Characteristic>
    </Service>
    <Service Type="local" PrimaryService="true">
        <Name>TX Power</Name>
        <Uuid>1804</Uuid>
        <Characteristic>
            <Name>TX Power Level</Name>
            <Uuid>2a07</Uuid>
            <DefaultValue>0</DefaultValue>
            <UsePresentationFormat>0</UsePresentationFormat>
            <UserDescription>The transmission signal strength. </UserDescription>
            <MaxDataLength>1</MaxDataLength>
            <AttributeLenType>1</AttributeLenType>
            <ForceOpen>false</ForceOpen>
            <Properties>
                <WriteWithoutResponse>false</WriteWithoutResponse>
                <Write>false</Write>
                <Notify>false</Notify>
                <Indicate>false</Indicate>
                <Broadcast>false</Broadcast>
            </Properties>
            <SetPipe>false</SetPipe>
            <AckIsAuto>false</AckIsAuto>
            <PresentationFormatDescriptor Value="0000" Exponent="0" Format="1" NameSpace="01" Unit="0000"/>
            <PeriodForReadingThisCharacteristic>0</PeriodForReadingThisCharacteristic>
            <PeriodForProperties/>
        </Characteristic>
    </Service>
    <Gapsettings>
        <Name>BLE</Name>
        <DeviceNameWriteLength>5</DeviceNameWriteLength>
        <LocalPipeOnDeviceName>true</LocalPipeOnDeviceName>
        <DeviceNameShortLength>0</DeviceNameShortLength>
        <Apperance>0000</Apperance>
        <SecurityLevel>0</SecurityLevel>
        <AuthenticationReq>0</AuthenticationReq>
        <IoCapabilities>0</IoCapabilities>
        <BondTimeout>600</BondTimeout>
        <SecurityRequestDelay>10</SecurityRequestDelay>
        <MinimumKeySize>7</MinimumKeySize>
        <MaximumKeySize>16</MaximumKeySize>
        <AdvertisingDataBondedBitmap>0</AdvertisingDataBondedBitmap>
        <AdvertisingDataGeneralBitmap>5a</AdvertisingDataGeneralBitmap>
        <AdvertisingDataBrodcastBitmap>0</AdvertisingDataBrodcastBitmap>
        <AdvertisingDataBondedScanResponseBitmap>0</AdvertisingDataBondedScanResponseBitmap>
        <AdvertisingDataGeneralScanResponseBitmap>0</AdvertisingDataGeneralScanResponseBitmap>
        <AdvertisingDataBrodcastScanResponseBitmap>0</AdvertisingDataBrodcastScanResponseBitmap>
        <AdvertisingDataBondedBitmapCustom>0</AdvertisingDataBondedBitmapCustom>
        <AdvertisingDataGeneralBitmapCustom>0</AdvertisingDataGeneralBitmapCustom>
        <AdvertisingDataBrodcastBitmapCustom>0</AdvertisingDataBrodcastBitmapCustom>
        <AdvertisingDataBondedScanResponseBitmapCustom>0</AdvertisingDataBondedScanResponseBitmapCustom>
        <AdvertisingDataGeneralScanResponseBitmapCustom>0</AdvertisingDataGeneralScanResponseBitmapCustom>
        <AdvertisingDataBrodcastScanResponseBitmapCustom>0</AdvertisingDataBrodcastScanResponseBitmapCustom>
        <TxPowerLevelOffset>0</TxPowerLevelOffset>
        <MinimumConnectionInterval>65535</MinimumConnectionInterval>
        <MaximumConnectionInterval>65535</MaximumConnectionInterval>
        <SlaveLatency>0</SlaveLatency>
        <TimeoutMultipler>65535</TimeoutMultipler>
        <ServiceToAdvertise>
            <Uuid BaseUUID="8C6B0000A312681D025B0032C0D16A2D" BaseUUIDName="BLEduino">2013</Uuid>
        </ServiceToAdvertise>
        <CustomAdTypes>
            <AdType index="1">
                <Type>0</Type>
                <Value></Value>
            </AdType>
            <AdType index="2">
                <Type>0</Type>
                <Value></Value>
            </AdType>
        </CustomAdTypes>
    </Gapsettings>
    <Hardwaresettings>
        <Clocksource>1</Clocksource>
        <ClockAccuracy>1</ClockAccuracy>
        <InitialTxPower>3</InitialTxPower>
        <HfClkSource>0</HfClkSource>
        <DcDcConverter>0</DcDcConverter>
        <ActiveSignalModeIndex>0</ActiveSignalModeIndex>
        <ActiveSignalToTickDistance>0</ActiveSignalToTickDistance>
        <DynamicWindowLimitingEnabled>false</DynamicWindowLimitingEnabled>
    </Hardwaresettings>
    <CurrentInput>
        <BatteryCharge>220</BatteryCharge>
        <Master32KhzClockAccuracy>10</Master32KhzClockAccuracy>
        <ConnectionInterval>1000</ConnectionInterval>
        <PercentOfTimeSleeping>0</PercentOfTimeSleeping>
        <PercentOfTimeAdvertising>0</PercentOfTimeAdvertising>
        <AdvertisingInterval>1280</AdvertisingInterval>
    </CurrentInput>
</Profile>
